cltools/__init__.py
cltools/configurable_runnable.py
cltools/exceptions.py
cltools/i18n.py
cltools/runnable.py
cltools/runner.py
cltools-0.5.0.dist-info/LICENSE
cltools-0.5.0.dist-info/WHEEL
cltools-0.5.0.dist-info/METADATA
cltools-0.5.0.dist-info/RECORD
