Metadata-Version: 2.1
Name: cltools
Version: 0.5.0
Summary: Set of decorators of to create transform a class into a command-line tool.
Home-page: https://github.com/gissehel/cltools
License: MIT
Keywords: cltools,commandline,tools,decorator
Author: Gissehel
Author-email: public-dev-cltools@gissehel.org
Classifier: Development Status :: 4 - Beta
Classifier: Environment :: Console
Classifier: Intended Audience :: Developers
Classifier: License :: OSI Approved :: MIT License
Classifier: Natural Language :: English
Classifier: Programming Language :: Python :: 2
Classifier: Programming Language :: Python :: 2.7
Classifier: Programming Language :: Python :: 3
Classifier: Programming Language :: Python :: 3.4
Classifier: Programming Language :: Python :: 3.5
Classifier: Programming Language :: Python :: 3.6
Classifier: Programming Language :: Python :: 3.7
Classifier: Programming Language :: Python :: 3.8
Classifier: Programming Language :: Python :: 3.9
Classifier: Topic :: System :: Shells
Classifier: Topic :: Terminals
Classifier: Topic :: Utilities
Project-URL: Documentation, https://github.com/gissehel/cltools
Project-URL: Repository, https://github.com/gissehel/cltools
